vipps_auth/apps.py
vipps_auth/client.py
vipps_auth/provider.py
vipps_auth/urls.py
vipps_auth/views.py
django_allauth_vipps-0.2.2.dist-info/LICENSE
django_allauth_vipps-0.2.2.dist-info/METADATA
django_allauth_vipps-0.2.2.dist-info/WHEEL
django_allauth_vipps-0.2.2.dist-info/RECORD
