Metadata-Version: 2.1
Name: django-allauth-vipps
Version: 0.2.2
Summary: A configurable Django Allauth provider for Vipps Login.
Home-page: https://github.com/danpejobo/django-allauth-vipps
License: MIT
Keywords: django,allauth,vipps,authentication,login
Author: Daniel Persen
Author-email: danpe_jobo@hotmail.com
Requires-Python: >=3.11,<4.0
Classifier: Environment :: Web Environment
Classifier: Framework :: Django
Classifier: Framework :: Django :: 5.1
Classifier: Intended Audience :: Developers
Classifier: License :: OSI Approved :: MIT License
Classifier: Operating System :: OS Independent
Classifier: Programming Language :: Python
Classifier: Programming Language :: Python :: 3
Classifier: Programming Language :: Python :: 3.11
Requires-Dist: django (>=4.2)
Requires-Dist: django-allauth[socialaccount] (>=65.9.0,<66.0.0)
Project-URL: Repository, https://github.com/danpejobo/django-allauth-vipps
